grabit_md/__init__.py
grabit_md/cli.py
grabit_md/grabber.py
grabit_md/py.typed
grabit_md/core/__init__.py
grabit_md/core/downloader.py
grabit_md/core/dtos.py
grabit_md/core/extractor.py
grabit_md/core/markdown_converter.py
grabit_md/core/misc.py
grabit_md/core/output_format.py
grabit_md/core/writer.py
grabit_md/grabbers/__init__.py
grabit_md/grabbers/base_grabber.py
grabit_md/grabbers/reddit_grabber.py
grabit_md-1.0.0.dist-info/licenses/LICENSE
grabit_md-1.0.0.dist-info/METADATA
grabit_md-1.0.0.dist-info/WHEEL
grabit_md-1.0.0.dist-info/entry_points.txt
grabit_md-1.0.0.dist-info/top_level.txt
grabit_md-1.0.0.dist-info/RECORD
