Metadata-Version: 2.4
Name: grabit-md
Version: 1.0.0
Summary: Grabit is a library that allows you to download web pages, extract their readable content, convert it to Markdown, and save it locally.
Author: Vlad Iliescu
License-Expression: LGPL-3.0
Keywords: python,markdown,cli,web scraping,downloader,scraper
Classifier: Programming Language :: Python :: 3
Classifier: Programming Language :: Python :: 3.11
Classifier: Programming Language :: Python :: 3.12
Classifier: Typing :: Typed
Requires-Python: >=3.11
License-File: LICENSE
Requires-Dist: readabilipy==0.3.0
Requires-Dist: markdownify==1.2.0
Requires-Dist: PyYAML==6.0.2
Requires-Dist: requests==2.32.5
Requires-Dist: mdformat==0.7.22
Requires-Dist: click<8.2,>=8.1.0
Dynamic: license-file
